{"data": [{"team_id": 664, "image_id": 3, "team_number": "18-2662", "image": "Server2022_cp18_sf_gsms", "duration": "03:02:02", "found": 3, "remaining": 29, "penalties": 1, "code": "", "ccs_score": 4, "location": "CA", "division": "Middle School", "tier": "Middle School"}, {"team_id": 664, "image_id": 4, "team_number": "18-2662", "image": "Mint21_cp18_sf_pgsms", "duration": "01:33:12", "found": 2, "remaining": 38, "penalties": 0, "code": "", "ccs_score": 2, "location": "CA", "division": "Middle School", "tier": "Middle School"}]}