{"data": [{"team_id": 81, "image_id": 4, "team_number": "18-0037", "image": "Server2022_cp18_state_pgsms", "duration": "03:49:20", "found": 23, "remaining": 8, "penalties": 0, "code": "", "ccs_score": 69, "location": "NJ", "division": "CAP", "tier": "Platinum"}, {"team_id": 81, "image_id": 5, "team_number": "18-0037", "image": "Ubuntu24_cp18_state_pg", "duration": "03:48:05", "found": 13, "remaining": 13, "penalties": 0, "code": "", "ccs_score": 55, "location": "NJ", "division": "CAP", "tier": "Platinum"}, {"team_id": 81, "image_id": 2, "team_number": "18-0037", "image": "Mint21_cp18_state_p", "duration": "03:47:52", "found": 19, "remaining": 19, "penalties": 0, "code": "", "ccs_score": 50, "location": "NJ", "division": "CAP", "tier": "Platinum"}]}