{"data": [{"team_id": 241, "image_id": 5, "team_number": "18-0779", "image": "Ubuntu24_cp18_state_pg", "duration": "03:50:49", "found": 16, "remaining": 10, "penalties": 0, "code": "", "ccs_score": 64, "location": "FL", "division": "Open", "tier": "Platinum"}, {"team_id": 241, "image_id": 4, "team_number": "18-0779", "image": "Server2022_cp18_state_pgsms", "duration": "03:55:19", "found": 17, "remaining": 14, "penalties": 0, "code": "", "ccs_score": 52, "location": "FL", "division": "Open", "tier": "Platinum"}, {"team_id": 241, "image_id": 2, "team_number": "18-0779", "image": "Mint21_cp18_state_p", "duration": "03:51:48", "found": 11, "remaining": 27, "penalties": 0, "code": "", "ccs_score": 24, "location": "FL", "division": "Open", "tier": "Platinum"}]}