{"data": [{"team_id": 243, "image_id": 2, "team_number": "18-0798", "image": "Mint21_cp18_state_p", "duration": "03:53:50", "found": 13, "remaining": 25, "penalties": 0, "code": "", "ccs_score": 22, "location": "CA", "division": "NJROTC", "tier": "Platinum"}, {"team_id": 243, "image_id": 5, "team_number": "18-0798", "image": "Ubuntu24_cp18_state_pg", "duration": "03:54:03", "found": 7, "remaining": 19, "penalties": 0, "code": "", "ccs_score": 22, "location": "CA", "division": "NJROTC", "tier": "Platinum"}, {"team_id": 243, "image_id": 4, "team_number": "18-0798", "image": "Server2022_cp18_state_pgsms", "duration": "03:52:21", "found": 8, "remaining": 23, "penalties": 0, "code": "", "ccs_score": 18, "location": "CA", "division": "NJROTC", "tier": "Platinum"}]}