{"data": [{"team_id": 147, "image_id": 2, "team_number": "18-0340", "image": "Mint21_cp18_state_p", "duration": "00:52:49", "found": 11, "remaining": 27, "penalties": 0, "code": "", "ccs_score": 24, "location": "TX", "division": "CAP", "tier": "Platinum"}, {"team_id": 147, "image_id": 5, "team_number": "18-0340", "image": "Ubuntu24_cp18_state_pg", "duration": "00:51:33", "found": 6, "remaining": 20, "penalties": 0, "code": "", "ccs_score": 20, "location": "TX", "division": "CAP", "tier": "Platinum"}, {"team_id": 147, "image_id": 4, "team_number": "18-0340", "image": "Server2022_cp18_state_pgsms", "duration": "02:02:45", "found": 8, "remaining": 23, "penalties": 0, "code": "", "ccs_score": 18, "location": "TX", "division": "CAP", "tier": "Platinum"}]}