{"data": [{"team_id": 392, "image_id": 2, "team_number": "18-1465", "image": "Mint21_cp18_state_p", "duration": "03:03:49", "found": 26, "remaining": 12, "penalties": 0, "code": "", "ccs_score": 72, "location": "VA", "division": "Open", "tier": "Platinum"}, {"team_id": 392, "image_id": 5, "team_number": "18-1465", "image": "Ubuntu24_cp18_state_pg", "duration": "02:55:29", "found": 18, "remaining": 8, "penalties": 0, "code": "", "ccs_score": 71, "location": "VA", "division": "Open", "tier": "Platinum"}, {"team_id": 392, "image_id": 4, "team_number": "18-1465", "image": "Server2022_cp18_state_pgsms", "duration": "03:41:36", "found": 17, "remaining": 14, "penalties": 0, "code": "", "ccs_score": 52, "location": "VA", "division": "Open", "tier": "Platinum"}]}