{"data": [{"team_id": 543, "image_id": 5, "team_number": "18-2075", "image": "Ubuntu24_cp18_state_pg", "duration": "03:45:49", "found": 13, "remaining": 13, "penalties": 0, "code": "", "ccs_score": 53, "location": "OK", "division": "Open", "tier": "Platinum"}, {"team_id": 543, "image_id": 4, "team_number": "18-2075", "image": "Server2022_cp18_state_pgsms", "duration": "03:52:50", "found": 19, "remaining": 12, "penalties": 0, "code": "", "ccs_score": 51, "location": "OK", "division": "Open", "tier": "Platinum"}, {"team_id": 543, "image_id": 2, "team_number": "18-2075", "image": "Mint21_cp18_state_p", "duration": "03:38:49", "found": 16, "remaining": 22, "penalties": 0, "code": "", "ccs_score": 46, "location": "OK", "division": "Open", "tier": "Platinum"}]}