{"data": [{"team_id": 197, "image_id": 5, "team_number": "18-0605", "image": "Ubuntu24_cp18_state_pg", "duration": "03:54:42", "found": 15, "remaining": 11, "penalties": 0, "code": "", "ccs_score": 58, "location": "VA", "division": "Open", "tier": "Platinum"}, {"team_id": 197, "image_id": 2, "team_number": "18-0605", "image": "Mint21_cp18_state_p", "duration": "03:51:39", "found": 24, "remaining": 14, "penalties": 0, "code": "", "ccs_score": 55, "location": "VA", "division": "Open", "tier": "Platinum"}, {"team_id": 197, "image_id": 4, "team_number": "18-0605", "image": "Server2022_cp18_state_pgsms", "duration": "03:55:50", "found": 15, "remaining": 16, "penalties": 0, "code": "", "ccs_score": 43, "location": "VA", "division": "Open", "tier": "Platinum"}]}