{"data": [{"team_id": 391, "image_id": 4, "team_number": "18-1464", "image": "Server2022_cp18_state_pgsms", "duration": "03:53:41", "found": 20, "remaining": 11, "penalties": 0, "code": "", "ccs_score": 60, "location": "VA", "division": "Open", "tier": "Platinum"}, {"team_id": 391, "image_id": 5, "team_number": "18-1464", "image": "Ubuntu24_cp18_state_pg", "duration": "03:52:50", "found": 14, "remaining": 12, "penalties": 0, "code": "", "ccs_score": 56, "location": "VA", "division": "Open", "tier": "Platinum"}, {"team_id": 391, "image_id": 2, "team_number": "18-1464", "image": "Mint21_cp18_state_p", "duration": "03:20:23", "found": 17, "remaining": 21, "penalties": 0, "code": "", "ccs_score": 53, "location": "VA", "division": "Open", "tier": "Platinum"}]}