{"data": [{"team_id": 592, "image_id": 2, "team_number": "18-2334", "image": "Mint21_cp18_state_p", "duration": "03:00:33", "found": 24, "remaining": 14, "penalties": 0, "code": "", "ccs_score": 58, "location": "ID", "division": "Open", "tier": "Platinum"}, {"team_id": 592, "image_id": 5, "team_number": "18-2334", "image": "Ubuntu24_cp18_state_pg", "duration": "03:06:20", "found": 10, "remaining": 16, "penalties": 0, "code": "", "ccs_score": 41, "location": "ID", "division": "Open", "tier": "Platinum"}, {"team_id": 592, "image_id": 4, "team_number": "18-2334", "image": "Server2022_cp18_state_pgsms", "duration": "03:38:50", "found": 10, "remaining": 21, "penalties": 0, "code": "", "ccs_score": 27, "location": "ID", "division": "Open", "tier": "Platinum"}]}