{"data": [{"team_id": 1824, "image_id": 5, "team_number": "18-3405", "image": "Ubuntu24_cp18_state_pg", "duration": "02:22:53", "found": 7, "remaining": 19, "penalties": 1, "code": "", "ccs_score": 24, "location": "CA", "division": "CAP", "tier": "Gold"}, {"team_id": 1824, "image_id": 3, "team_number": "18-3405", "image": "Mint21_cp18_state_gsms", "duration": "01:00:50", "found": 5, "remaining": 27, "penalties": 0, "code": "", "ccs_score": 12, "location": "CA", "division": "CAP", "tier": "Gold"}, {"team_id": 1824, "image_id": 4, "team_number": "18-3405", "image": "Server2022_cp18_state_pgsms", "duration": "02:30:46", "found": 5, "remaining": 26, "penalties": 0, "code": "", "ccs_score": 11, "location": "CA", "division": "CAP", "tier": "Gold"}]}