{"data": [{"team_id": 2087, "image_id": 3, "team_number": "18-4647", "image": "Mint21_cp18_state_gsms", "duration": "03:54:47", "found": 6, "remaining": 26, "penalties": 0, "code": "", "ccs_score": 24, "location": "VA", "division": "Open", "tier": "Gold"}, {"team_id": 2087, "image_id": 5, "team_number": "18-4647", "image": "Ubuntu24_cp18_state_pg", "duration": "03:54:51", "found": 3, "remaining": 23, "penalties": 0, "code": "", "ccs_score": 15, "location": "VA", "division": "Open", "tier": "Gold"}, {"team_id": 2087, "image_id": 4, "team_number": "18-4647", "image": "Server2022_cp18_state_pgsms", "duration": "03:55:50", "found": 7, "remaining": 24, "penalties": 0, "code": "", "ccs_score": 15, "location": "VA", "division": "Open", "tier": "Gold"}]}