{"data": [{"team_id": 3023, "image_id": 3, "team_number": "18-0354", "image": "Mint21_cp18_state_gsms", "duration": "01:58:51", "found": 7, "remaining": 25, "penalties": 0, "code": "", "ccs_score": 26, "location": "MI", "division": "Middle School", "tier": "Middle School"}, {"team_id": 3023, "image_id": 1, "team_number": "18-0354", "image": "Ubuntu24_cp18_state_sms", "duration": "03:00:42", "found": 3, "remaining": 15, "penalties": 0, "code": "", "ccs_score": 15, "location": "MI", "division": "Middle School", "tier": "Middle School"}, {"team_id": 3023, "image_id": 4, "team_number": "18-0354", "image": "Server2022_cp18_state_pgsms", "duration": "02:25:47", "found": 5, "remaining": 26, "penalties": 1, "code": "", "ccs_score": 5, "location": "MI", "division": "Middle School", "tier": "Middle School"}]}