{"data": [{"team_id": 3006, "image_id": 4, "team_number": "18-0200", "image": "Server2022_cp18_state_pgsms", "duration": "03:49:50", "found": 14, "remaining": 17, "penalties": 0, "code": "", "ccs_score": 37, "location": "MO", "division": "Middle School", "tier": "Middle School"}, {"team_id": 3006, "image_id": 1, "team_number": "18-0200", "image": "Ubuntu24_cp18_state_sms", "duration": "03:48:34", "found": 5, "remaining": 13, "penalties": 0, "code": "", "ccs_score": 30, "location": "MO", "division": "Middle School", "tier": "Middle School"}, {"team_id": 3006, "image_id": 3, "team_number": "18-0200", "image": "Mint21_cp18_state_gsms", "duration": "02:15:13", "found": 4, "remaining": 28, "penalties": 0, "code": "", "ccs_score": 13, "location": "MO", "division": "Middle School", "tier": "Middle School"}]}