{"data": [{"team_id": 277, "image_id": 5, "team_number": "18-0989", "image": "Ubuntu24_cp18_state_pg", "duration": "03:55:47", "found": 22, "remaining": 4, "penalties": 0, "code": "", "ccs_score": 83, "location": "CAN", "division": "Open", "tier": "Platinum"}, {"team_id": 277, "image_id": 2, "team_number": "18-0989", "image": "Mint21_cp18_state_p", "duration": "03:55:43", "found": 31, "remaining": 7, "penalties": 0, "code": "", "ccs_score": 78, "location": "CAN", "division": "Open", "tier": "Platinum"}, {"team_id": 277, "image_id": 4, "team_number": "18-0989", "image": "Server2022_cp18_state_pgsms", "duration": "03:57:50", "found": 19, "remaining": 12, "penalties": 0, "code": "", "ccs_score": 53, "location": "CAN", "division": "Open", "tier": "Platinum"}]}