{"data": [{"team_id": 2448, "image_id": 1, "team_number": "18-2229", "image": "Ubuntu24_cp18_state_sms", "duration": "02:46:09", "found": 7, "remaining": 11, "penalties": 0, "code": "", "ccs_score": 45, "location": "GA", "division": "CAP", "tier": "Silver"}, {"team_id": 2448, "image_id": 4, "team_number": "18-2229", "image": "Server2022_cp18_state_pgsms", "duration": "02:48:50", "found": 8, "remaining": 23, "penalties": 0, "code": "", "ccs_score": 18, "location": "GA", "division": "CAP", "tier": "Silver"}, {"team_id": 2448, "image_id": 3, "team_number": "18-2229", "image": "Mint21_cp18_state_gsms", "duration": "00:25:49", "found": 2, "remaining": 30, "penalties": 0, "code": "", "ccs_score": 9, "location": "GA", "division": "CAP", "tier": "Silver"}]}