{"data": [{"team_id": 2430, "image_id": 1, "team_number": "18-2142", "image": "Ubuntu24_cp18_state_sms", "duration": "03:09:56", "found": 9, "remaining": 9, "penalties": 1, "code": "", "ccs_score": 50, "location": "IA", "division": "Open", "tier": "Silver"}, {"team_id": 2430, "image_id": 3, "team_number": "18-2142", "image": "Mint21_cp18_state_gsms", "duration": "02:56:48", "found": 7, "remaining": 25, "penalties": 0, "code": "", "ccs_score": 21, "location": "IA", "division": "Open", "tier": "Silver"}, {"team_id": 2430, "image_id": 4, "team_number": "18-2142", "image": "Server2022_cp18_state_pgsms", "duration": "03:25:42", "found": 8, "remaining": 23, "penalties": 0, "code": "", "ccs_score": 18, "location": "IA", "division": "Open", "tier": "Silver"}]}