{"data": [{"team_id": 2983, "image_id": 4, "team_number": "18-4896", "image": "Server2022_cp18_state_pgsms", "duration": "03:11:50", "found": 7, "remaining": 24, "penalties": 0, "code": "", "ccs_score": 16, "location": "TX", "division": "MCJROTC", "tier": "Silver"}, {"team_id": 2983, "image_id": 1, "team_number": "18-4896", "image": "Ubuntu24_cp18_state_sms", "duration": "03:09:12", "found": 0, "remaining": 18, "penalties": 0, "code": "", "ccs_score": 0, "location": "TX", "division": "MCJROTC", "tier": "Silver"}]}