{"data": [{"team_id": 52, "image_id": 3, "team_number": "17-1245", "image": "Server2022_cp17_sf_pgsms", "duration": "03:17:50", "found": 19, "remaining": 17, "penalties": 0, "code": "", "ccs_score": 52, "location": "IN", "division": "Open", "tier": "Platinum"}, {"team_id": 52, "image_id": 4, "team_number": "17-1245", "image": "Windows11_cp17_sf_pg", "duration": "03:17:52", "found": 19, "remaining": 22, "penalties": 0, "code": "", "ccs_score": 41, "location": "IN", "division": "Open", "tier": "Platinum"}, {"team_id": 52, "image_id": 1, "team_number": "17-1245", "image": "Mint21_cp17_sf_p", "duration": "03:17:03", "found": 7, "remaining": 37, "penalties": 0, "code": "", "ccs_score": 11, "location": "IN", "division": "Open", "tier": "Platinum"}]}