{"data": [{"team_id": 672, "image_id": 4, "team_number": "17-0611", "image": "Server2019_cp17_state_pg", "duration": "03:52:41", "found": 10, "remaining": 21, "penalties": 0, "code": "", "ccs_score": 32, "location": "SC", "division": "AJROTC", "tier": "Platinum"}, {"team_id": 672, "image_id": 1, "team_number": "17-0611", "image": "Windows10_cp17_state_pgsms", "duration": "03:53:50", "found": 11, "remaining": 20, "penalties": 0, "code": "", "ccs_score": 30, "location": "SC", "division": "AJROTC", "tier": "Platinum"}, {"team_id": 672, "image_id": 3, "team_number": "17-0611", "image": "Ubuntu22_cp17_state_p", "duration": "03:52:48", "found": 9, "remaining": 31, "penalties": 0, "code": "", "ccs_score": 23, "location": "SC", "division": "AJROTC", "tier": "Platinum"}]}