{"data": [{"team_id": 890, "image_id": 1, "team_number": "17-1182", "image": "Windows10_cp17_state_pgsms", "duration": "03:58:02", "found": 19, "remaining": 12, "penalties": 0, "code": "", "ccs_score": 61, "location": "FL", "division": "NJROTC", "tier": "Platinum"}, {"team_id": 890, "image_id": 4, "team_number": "17-1182", "image": "Server2019_cp17_state_pg", "duration": "03:49:36", "found": 17, "remaining": 14, "penalties": 0, "code": "", "ccs_score": 51, "location": "FL", "division": "NJROTC", "tier": "Platinum"}, {"team_id": 890, "image_id": 3, "team_number": "17-1182", "image": "Ubuntu22_cp17_state_p", "duration": "03:58:49", "found": 11, "remaining": 29, "penalties": 0, "code": "", "ccs_score": 29, "location": "FL", "division": "NJROTC", "tier": "Platinum"}]}