{"data": [{"team_id": 245, "image_id": 4, "team_number": "17-1319", "image": "Server2019_cp17_state_pg", "duration": "03:57:46", "found": 18, "remaining": 13, "penalties": 0, "code": "", "ccs_score": 60, "location": "VA", "division": "Open", "tier": "Platinum"}, {"team_id": 245, "image_id": 1, "team_number": "17-1319", "image": "Windows10_cp17_state_pgsms", "duration": "03:57:50", "found": 16, "remaining": 15, "penalties": 0, "code": "", "ccs_score": 54, "location": "VA", "division": "Open", "tier": "Platinum"}, {"team_id": 245, "image_id": 3, "team_number": "17-1319", "image": "Ubuntu22_cp17_state_p", "duration": "03:54:31", "found": 19, "remaining": 21, "penalties": 0, "code": "", "ccs_score": 46, "location": "VA", "division": "Open", "tier": "Platinum"}]}