{"data": [{"team_id": 2124, "image_id": 5, "team_number": "17-2814", "image": "Ubuntu22_cp17_state_gsms", "duration": "02:35:25", "found": 6, "remaining": 23, "penalties": 0, "code": "", "ccs_score": 19, "location": "VA", "division": "NJROTC", "tier": "Gold"}, {"team_id": 2124, "image_id": 1, "team_number": "17-2814", "image": "Windows10_cp17_state_pgsms", "duration": "02:39:43", "found": 5, "remaining": 26, "penalties": 1, "code": "", "ccs_score": 8, "location": "VA", "division": "NJROTC", "tier": "Gold"}]}