{"data": [{"team_id": 539, "image_id": 4, "team_number": "17-3446", "image": "Server2019_cp17_state_pg", "duration": "03:51:47", "found": 27, "remaining": 4, "penalties": 0, "code": "", "ccs_score": 85, "location": "TX", "division": "Open", "tier": "Platinum"}, {"team_id": 539, "image_id": 1, "team_number": "17-3446", "image": "Windows10_cp17_state_pgsms", "duration": "03:29:18", "found": 22, "remaining": 9, "penalties": 0, "code": "", "ccs_score": 72, "location": "TX", "division": "Open", "tier": "Platinum"}, {"team_id": 539, "image_id": 3, "team_number": "17-3446", "image": "Ubuntu22_cp17_state_p", "duration": "03:31:49", "found": 28, "remaining": 12, "penalties": 0, "code": "", "ccs_score": 68, "location": "TX", "division": "Open", "tier": "Platinum"}]}