{"data": [{"team_id": 2602, "image_id": 2, "team_number": "17-3866", "image": "Server2019_cp17_state_sms", "duration": "01:26:32", "found": 14, "remaining": 11, "penalties": 0, "code": "", "ccs_score": 51, "location": "NC", "division": "Open", "tier": "Silver"}, {"team_id": 2602, "image_id": 5, "team_number": "17-3866", "image": "Ubuntu22_cp17_state_gsms", "duration": "00:50:18", "found": 9, "remaining": 20, "penalties": 0, "code": "", "ccs_score": 33, "location": "NC", "division": "Open", "tier": "Silver"}, {"team_id": 2602, "image_id": 1, "team_number": "17-3866", "image": "Windows10_cp17_state_pgsms", "duration": "01:17:27", "found": 10, "remaining": 21, "penalties": 0, "code": "", "ccs_score": 30, "location": "NC", "division": "Open", "tier": "Silver"}]}