{"data": [{"team_id": 688, "image_id": 1, "team_number": "17-3178", "image": "Windows10_cp17_state_pgsms", "duration": "03:20:28", "found": 14, "remaining": 17, "penalties": 0, "code": "", "ccs_score": 39, "location": "VA", "division": "AJROTC", "tier": "Platinum"}, {"team_id": 688, "image_id": 4, "team_number": "17-3178", "image": "Server2019_cp17_state_pg", "duration": "03:24:50", "found": 16, "remaining": 15, "penalties": 2, "code": "", "ccs_score": 36, "location": "VA", "division": "AJROTC", "tier": "Platinum"}, {"team_id": 688, "image_id": 3, "team_number": "17-3178", "image": "Ubuntu22_cp17_state_p", "duration": "03:43:47", "found": 11, "remaining": 29, "penalties": 0, "code": "", "ccs_score": 26, "location": "VA", "division": "AJROTC", "tier": "Platinum"}]}