{"data": [{"team_id": 504, "image_id": 4, "team_number": "17-3221", "image": "Server2019_cp17_state_pg", "duration": "03:48:46", "found": 25, "remaining": 6, "penalties": 0, "code": "", "ccs_score": 80, "location": "MI", "division": "Open", "tier": "Platinum"}, {"team_id": 504, "image_id": 1, "team_number": "17-3221", "image": "Windows10_cp17_state_pgsms", "duration": "03:48:50", "found": 16, "remaining": 15, "penalties": 0, "code": "", "ccs_score": 55, "location": "MI", "division": "Open", "tier": "Platinum"}, {"team_id": 504, "image_id": 3, "team_number": "17-3221", "image": "Ubuntu22_cp17_state_p", "duration": "03:46:41", "found": 13, "remaining": 27, "penalties": 0, "code": "", "ccs_score": 34, "location": "MI", "division": "Open", "tier": "Platinum"}]}