{"data": [{"team_id": 2655, "image_id": 2, "team_number": "17-4125", "image": "Server2019_cp17_state_sms", "duration": "03:57:50", "found": 18, "remaining": 7, "penalties": 0, "code": "", "ccs_score": 69, "location": "TX", "division": "Open", "tier": "Silver"}, {"team_id": 2655, "image_id": 5, "team_number": "17-4125", "image": "Ubuntu22_cp17_state_gsms", "duration": "03:57:48", "found": 13, "remaining": 16, "penalties": 0, "code": "", "ccs_score": 47, "location": "TX", "division": "Open", "tier": "Silver"}, {"team_id": 2655, "image_id": 1, "team_number": "17-4125", "image": "Windows10_cp17_state_pgsms", "duration": "03:52:28", "found": 14, "remaining": 17, "penalties": 0, "code": "", "ccs_score": 46, "location": "TX", "division": "Open", "tier": "Silver"}]}