{"data": [{"team_id": 1730, "image_id": 1, "team_number": "17-4463", "image": "Windows10_cp17_state_pgsms", "duration": "03:46:04", "found": 15, "remaining": 16, "penalties": 0, "code": "", "ccs_score": 48, "location": "CA", "division": "Open", "tier": "Gold"}, {"team_id": 1730, "image_id": 4, "team_number": "17-4463", "image": "Server2019_cp17_state_pg", "duration": "03:35:27", "found": 15, "remaining": 16, "penalties": 0, "code": "", "ccs_score": 45, "location": "CA", "division": "Open", "tier": "Gold"}, {"team_id": 1730, "image_id": 5, "team_number": "17-4463", "image": "Ubuntu22_cp17_state_gsms", "duration": "03:42:28", "found": 13, "remaining": 16, "penalties": 0, "code": "", "ccs_score": 45, "location": "CA", "division": "Open", "tier": "Gold"}]}