{"data": [{"team_id": 664, "image_id": 4, "team_number": "17-0710", "image": "Mint21_cp17_r2_hs", "duration": "03:55:48", "found": 29, "remaining": 1, "penalties": 0, "code": "", "ccs_score": 97, "location": "MO", "division": "CAP"}, {"team_id": 664, "image_id": 2, "team_number": "17-0710", "image": "Windows11_cp17_intro_r2_hsms", "duration": "03:55:49", "found": 18, "remaining": 2, "penalties": 0, "code": "", "ccs_score": 90, "location": "MO", "division": "CAP"}, {"team_id": 664, "image_id": 3, "team_number": "17-0710", "image": "Server2022_cp17_r2_hs", "duration": "03:40:46", "found": 23, "remaining": 5, "penalties": 0, "code": "", "ccs_score": 78, "location": "MO", "division": "CAP"}]}