{"data": [{"team_id": 724, "image_id": 2, "team_number": "17-0778", "image": "Windows11_cp17_intro_r2_hsms", "duration": "03:24:50", "found": 19, "remaining": 1, "penalties": 0, "code": "", "ccs_score": 95, "location": "MD", "division": "Open"}, {"team_id": 724, "image_id": 4, "team_number": "17-0778", "image": "Mint21_cp17_r2_hs", "duration": "03:57:21", "found": 22, "remaining": 8, "penalties": 0, "code": "", "ccs_score": 75, "location": "MD", "division": "Open"}, {"team_id": 724, "image_id": 3, "team_number": "17-0778", "image": "Server2022_cp17_r2_hs", "duration": "02:15:05", "found": 18, "remaining": 10, "penalties": 0, "code": "", "ccs_score": 65, "location": "MD", "division": "Open"}]}