{"data": [{"team_id": 1304, "image_id": 2, "team_number": "17-1402", "image": "Windows11_cp17_intro_r2_hsms", "duration": "03:33:50", "found": 18, "remaining": 2, "penalties": 0, "code": "", "ccs_score": 90, "location": "VA", "division": "Open"}, {"team_id": 1304, "image_id": 3, "team_number": "17-1402", "image": "Server2022_cp17_r2_hs", "duration": "03:41:46", "found": 16, "remaining": 12, "penalties": 0, "code": "", "ccs_score": 64, "location": "VA", "division": "Open"}, {"team_id": 1304, "image_id": 4, "team_number": "17-1402", "image": "Mint21_cp17_r2_hs", "duration": "03:43:25", "found": 18, "remaining": 12, "penalties": 0, "code": "", "ccs_score": 60, "location": "VA", "division": "Open"}]}