{"data": [{"team_id": 1739, "image_id": 2, "team_number": "17-1883", "image": "Windows11_cp17_intro_r2_hsms", "duration": "03:58:36", "found": 12, "remaining": 8, "penalties": 0, "code": "T", "ccs_score": 62, "location": "NC", "division": "Open"}, {"team_id": 1739, "image_id": 4, "team_number": "17-1883", "image": "Mint21_cp17_r2_hs", "duration": "04:00:52", "found": 13, "remaining": 17, "penalties": 2, "code": "T", "ccs_score": 30, "location": "NC", "division": "Open"}, {"team_id": 1739, "image_id": 3, "team_number": "17-1883", "image": "Server2022_cp17_r2_hs", "duration": "04:00:16", "found": 7, "remaining": 21, "penalties": 1, "code": "T", "ccs_score": 22, "location": "NC", "division": "Open"}]}