{"data": [{"team_id": 1916, "image_id": 2, "team_number": "17-2080", "image": "Windows11_cp17_intro_r2_hsms", "duration": "03:43:02", "found": 13, "remaining": 7, "penalties": 0, "code": "", "ccs_score": 65, "location": "AK", "division": "Open"}, {"team_id": 1916, "image_id": 3, "team_number": "17-2080", "image": "Server2022_cp17_r2_hs", "duration": "02:11:02", "found": 14, "remaining": 14, "penalties": 0, "code": "", "ccs_score": 53, "location": "AK", "division": "Open"}, {"team_id": 1916, "image_id": 4, "team_number": "17-2080", "image": "Mint21_cp17_r2_hs", "duration": "03:27:49", "found": 15, "remaining": 15, "penalties": 0, "code": "", "ccs_score": 51, "location": "AK", "division": "Open"}]}