{"data": [{"team_id": 2031, "image_id": 2, "team_number": "17-2198", "image": "Windows11_cp17_intro_r2_hsms", "duration": "02:48:02", "found": 10, "remaining": 10, "penalties": 0, "code": "", "ccs_score": 45, "location": "TX", "division": "NJROTC"}, {"team_id": 2031, "image_id": 3, "team_number": "17-2198", "image": "Server2022_cp17_r2_hs", "duration": "03:30:50", "found": 10, "remaining": 18, "penalties": 0, "code": "", "ccs_score": 37, "location": "TX", "division": "NJROTC"}, {"team_id": 2031, "image_id": 4, "team_number": "17-2198", "image": "Mint21_cp17_r2_hs", "duration": "02:44:29", "found": 6, "remaining": 24, "penalties": 0, "code": "", "ccs_score": 21, "location": "TX", "division": "NJROTC"}]}