{"data": [{"team_id": 1937, "image_id": 4, "team_number": "17-2101", "image": "Mint21_cp17_r2_hs", "duration": "03:22:51", "found": 17, "remaining": 13, "penalties": 0, "code": "", "ccs_score": 58, "location": "VA", "division": "NJROTC"}, {"team_id": 1937, "image_id": 3, "team_number": "17-2101", "image": "Server2022_cp17_r2_hs", "duration": "03:22:27", "found": 15, "remaining": 13, "penalties": 0, "code": "", "ccs_score": 54, "location": "VA", "division": "NJROTC"}, {"team_id": 1937, "image_id": 2, "team_number": "17-2101", "image": "Windows11_cp17_intro_r2_hsms", "duration": "02:09:44", "found": 12, "remaining": 8, "penalties": 1, "code": "", "ccs_score": 50, "location": "VA", "division": "NJROTC"}]}