{"data": [{"team_id": 3573, "image_id": 2, "team_number": "17-3804", "image": "Windows11_cp17_intro_r2_hsms", "duration": "02:04:17", "found": 16, "remaining": 4, "penalties": 0, "code": "", "ccs_score": 79, "location": "CO", "division": "Open"}, {"team_id": 3573, "image_id": 3, "team_number": "17-3804", "image": "Server2022_cp17_r2_hs", "duration": "02:03:50", "found": 13, "remaining": 15, "penalties": 0, "code": "", "ccs_score": 51, "location": "CO", "division": "Open"}, {"team_id": 3573, "image_id": 4, "team_number": "17-3804", "image": "Mint21_cp17_r2_hs", "duration": "02:03:48", "found": 1, "remaining": 29, "penalties": 0, "code": "", "ccs_score": 6, "location": "CO", "division": "Open"}]}