{"data": [{"team_id": 4701, "image_id": 2, "team_number": "17-4994", "image": "Windows11_cp17_intro_r2_hsms", "duration": "02:57:36", "found": 17, "remaining": 3, "penalties": 0, "code": "", "ccs_score": 85, "location": "MD", "division": "Open"}, {"team_id": 4701, "image_id": 4, "team_number": "17-4994", "image": "Mint21_cp17_r2_hs", "duration": "03:35:30", "found": 21, "remaining": 9, "penalties": 0, "code": "", "ccs_score": 72, "location": "MD", "division": "Open"}, {"team_id": 4701, "image_id": 3, "team_number": "17-4994", "image": "Server2022_cp17_r2_hs", "duration": "03:43:50", "found": 14, "remaining": 14, "penalties": 0, "code": "", "ccs_score": 53, "location": "MD", "division": "Open"}]}