{"data": [{"team_id": 4155, "image_id": 3, "team_number": "17-4418", "image": "Server2022_cp17_r2_hs", "duration": "03:34:28", "found": 12, "remaining": 16, "penalties": 0, "code": "", "ccs_score": 43, "location": "VA", "division": "Open"}, {"team_id": 4155, "image_id": 4, "team_number": "17-4418", "image": "Mint21_cp17_r2_hs", "duration": "02:38:02", "found": 10, "remaining": 20, "penalties": 0, "code": "", "ccs_score": 36, "location": "VA", "division": "Open"}, {"team_id": 4155, "image_id": 2, "team_number": "17-4418", "image": "Windows11_cp17_intro_r2_hsms", "duration": "23:16:50", "found": 1, "remaining": 19, "penalties": 0, "code": "MT", "ccs_score": 4, "location": "VA", "division": "Open"}]}