{"data": [{"team_id": 4669, "image_id": 2, "team_number": "17-4960", "image": "Windows11_cp17_intro_r2_hsms", "duration": "03:21:59", "found": 16, "remaining": 4, "penalties": 0, "code": "", "ccs_score": 79, "location": "FL", "division": "AFJROTC"}, {"team_id": 4669, "image_id": 3, "team_number": "17-4960", "image": "Server2022_cp17_r2_hs", "duration": "03:59:50", "found": 13, "remaining": 15, "penalties": 0, "code": "", "ccs_score": 51, "location": "FL", "division": "AFJROTC"}, {"team_id": 4669, "image_id": 4, "team_number": "17-4960", "image": "Mint21_cp17_r2_hs", "duration": "03:12:08", "found": 4, "remaining": 26, "penalties": 0, "code": "", "ccs_score": 12, "location": "FL", "division": "AFJROTC"}]}