{"data": [{"team_id": 1945, "image_id": 3, "team_number": "18-1939", "image": "Windows11_cp18_sp", "duration": "02:32:51", "found": 24, "remaining": 0, "penalties": 0, "code": "M", "ccs_score": 100, "location": "MD", "division": "Open", "tier": "High School"}, {"team_id": 1945, "image_id": 7, "team_number": "18-1939", "image": "Mint21_cp18_sp", "duration": "01:07:23", "found": 16, "remaining": 3, "penalties": 0, "code": "", "ccs_score": 83, "location": "MD", "division": "Open", "tier": "High School"}]}