{"data": [{"team_id": 1251, "image_id": 7, "team_number": "18-1223", "image": "Mint21_cp18_sp", "duration": "04:05:50", "found": 15, "remaining": 4, "penalties": 0, "code": "", "ccs_score": 77, "location": "FL", "division": "Middle School", "tier": "Middle School"}, {"team_id": 1251, "image_id": 3, "team_number": "18-1223", "image": "Windows11_cp18_sp", "duration": "04:05:39", "found": 12, "remaining": 12, "penalties": 0, "code": "", "ccs_score": 49, "location": "FL", "division": "Middle School", "tier": "Middle School"}]}