{"data": [{"team_id": 2507, "image_id": 7, "team_number": "18-2514", "image": "Mint21_cp18_sp", "duration": "01:25:33", "found": 17, "remaining": 2, "penalties": 0, "code": "", "ccs_score": 89, "location": "AR", "division": "Open", "tier": "High School"}, {"team_id": 2507, "image_id": 3, "team_number": "18-2514", "image": "Windows11_cp18_sp", "duration": "01:27:50", "found": 20, "remaining": 4, "penalties": 0, "code": "", "ccs_score": 83, "location": "AR", "division": "Open", "tier": "High School"}]}