{"data": [{"team_id": 2831, "image_id": 3, "team_number": "18-2843", "image": "Windows11_cp18_sp", "duration": "03:46:50", "found": 18, "remaining": 6, "penalties": 1, "code": "", "ccs_score": 67, "location": "FL", "division": "AJROTC", "tier": "High School"}, {"team_id": 2831, "image_id": 7, "team_number": "18-2843", "image": "Mint21_cp18_sp", "duration": "03:21:36", "found": 12, "remaining": 7, "penalties": 0, "code": "", "ccs_score": 63, "location": "FL", "division": "AJROTC", "tier": "High School"}]}