{"data": [{"team_id": 2678, "image_id": 3, "team_number": "18-2687", "image": "Windows11_cp18_sp", "duration": "00:45:48", "found": 12, "remaining": 12, "penalties": 0, "code": "", "ccs_score": 51, "location": "CA", "division": "Open", "tier": "High School"}, {"team_id": 2678, "image_id": 7, "team_number": "18-2687", "image": "Mint21_cp18_sp", "duration": "00:41:51", "found": 2, "remaining": 17, "penalties": 0, "code": "", "ccs_score": 16, "location": "CA", "division": "Open", "tier": "High School"}]}