{"data": [{"team_id": 1108, "image_id": 5, "team_number": "17-0879", "image": "Ubuntu22_cp17_state_gsms", "duration": "03:57:05", "found": 17, "remaining": 12, "penalties": 0, "code": "", "ccs_score": 58, "location": "TX", "division": "Open", "tier": "Gold"}, {"team_id": 1108, "image_id": 1, "team_number": "17-0879", "image": "Windows10_cp17_state_pgsms", "duration": "03:46:50", "found": 15, "remaining": 16, "penalties": 0, "code": "", "ccs_score": 45, "location": "TX", "division": "Open", "tier": "Gold"}, {"team_id": 1108, "image_id": 4, "team_number": "17-0879", "image": "Server2019_cp17_state_pg", "duration": "03:43:59", "found": 13, "remaining": 18, "penalties": 1, "code": "", "ccs_score": 40, "location": "TX", "division": "Open", "tier": "Gold"}]}