{"data": [{"team_id": 868, "image_id": 4, "team_number": "17-0191", "image": "Server2019_cp17_state_pg", "duration": "03:58:50", "found": 15, "remaining": 16, "penalties": 0, "code": "", "ccs_score": 45, "location": "TX", "division": "NJROTC", "tier": "Platinum"}, {"team_id": 868, "image_id": 1, "team_number": "17-0191", "image": "Windows10_cp17_state_pgsms", "duration": "03:08:14", "found": 13, "remaining": 18, "penalties": 0, "code": "", "ccs_score": 43, "location": "TX", "division": "NJROTC", "tier": "Platinum"}, {"team_id": 868, "image_id": 3, "team_number": "17-0191", "image": "Ubuntu22_cp17_state_p", "duration": "03:34:41", "found": 14, "remaining": 26, "penalties": 0, "code": "", "ccs_score": 35, "location": "TX", "division": "NJROTC", "tier": "Platinum"}]}