{"data": [{"team_id": 3464, "image_id": 5, "team_number": "17-1959", "image": "Ubuntu22_cp17_state_gsms", "duration": "03:27:26", "found": 18, "remaining": 11, "penalties": 1, "code": "", "ccs_score": 60, "location": "CA", "division": "Middle School", "tier": "Middle School"}, {"team_id": 3464, "image_id": 2, "team_number": "17-1959", "image": "Server2019_cp17_state_sms", "duration": "03:44:50", "found": 14, "remaining": 11, "penalties": 0, "code": "", "ccs_score": 53, "location": "CA", "division": "Middle School", "tier": "Middle School"}, {"team_id": 3464, "image_id": 1, "team_number": "17-1959", "image": "Windows10_cp17_state_pgsms", "duration": "03:05:41", "found": 15, "remaining": 16, "penalties": 0, "code": "", "ccs_score": 49, "location": "CA", "division": "Middle School", "tier": "Middle School"}]}