{"data": [{"team_id": 1360, "image_id": 4, "team_number": "17-2281", "image": "Server2019_cp17_state_pg", "duration": "03:30:51", "found": 21, "remaining": 10, "penalties": 0, "code": "", "ccs_score": 66, "location": "FL", "division": "Open", "tier": "Gold"}, {"team_id": 1360, "image_id": 5, "team_number": "17-2281", "image": "Ubuntu22_cp17_state_gsms", "duration": "03:47:14", "found": 17, "remaining": 12, "penalties": 0, "code": "", "ccs_score": 63, "location": "FL", "division": "Open", "tier": "Gold"}, {"team_id": 1360, "image_id": 1, "team_number": "17-2281", "image": "Windows10_cp17_state_pgsms", "duration": "03:21:50", "found": 11, "remaining": 20, "penalties": 0, "code": "", "ccs_score": 33, "location": "FL", "division": "Open", "tier": "Gold"}]}