{"data": [{"team_id": 1317, "image_id": 4, "team_number": "17-2020", "image": "Server2019_cp17_state_pg", "duration": "03:52:37", "found": 11, "remaining": 20, "penalties": 0, "code": "", "ccs_score": 35, "location": "OH", "division": "Open", "tier": "Gold"}, {"team_id": 1317, "image_id": 5, "team_number": "17-2020", "image": "Ubuntu22_cp17_state_gsms", "duration": "03:52:19", "found": 7, "remaining": 22, "penalties": 0, "code": "", "ccs_score": 25, "location": "OH", "division": "Open", "tier": "Gold"}, {"team_id": 1317, "image_id": 1, "team_number": "17-2020", "image": "Windows10_cp17_state_pgsms", "duration": "03:53:53", "found": 7, "remaining": 24, "penalties": 0, "code": "", "ccs_score": 21, "location": "OH", "division": "Open", "tier": "Gold"}]}