{"data": [{"team_id": 915, "image_id": 1, "team_number": "17-2559", "image": "Windows10_cp17_state_pgsms", "duration": "03:15:54", "found": 14, "remaining": 17, "penalties": 0, "code": "", "ccs_score": 45, "location": "AL", "division": "NJROTC", "tier": "Platinum"}, {"team_id": 915, "image_id": 4, "team_number": "17-2559", "image": "Server2019_cp17_state_pg", "duration": "03:51:39", "found": 10, "remaining": 21, "penalties": 1, "code": "", "ccs_score": 30, "location": "AL", "division": "NJROTC", "tier": "Platinum"}, {"team_id": 915, "image_id": 3, "team_number": "17-2559", "image": "Ubuntu22_cp17_state_p", "duration": "03:30:51", "found": 7, "remaining": 33, "penalties": 0, "code": "", "ccs_score": 15, "location": "AL", "division": "NJROTC", "tier": "Platinum"}]}