{"data": [{"team_id": 564, "image_id": 4, "team_number": "17-3683", "image": "Server2019_cp17_state_pg", "duration": "03:54:33", "found": 28, "remaining": 3, "penalties": 0, "code": "", "ccs_score": 88, "location": "MD", "division": "Open", "tier": "Platinum"}, {"team_id": 564, "image_id": 1, "team_number": "17-3683", "image": "Windows10_cp17_state_pgsms", "duration": "03:52:41", "found": 26, "remaining": 5, "penalties": 0, "code": "", "ccs_score": 85, "location": "MD", "division": "Open", "tier": "Platinum"}, {"team_id": 564, "image_id": 3, "team_number": "17-3683", "image": "Ubuntu22_cp17_state_p", "duration": "03:36:50", "found": 25, "remaining": 15, "penalties": 0, "code": "", "ccs_score": 61, "location": "MD", "division": "Open", "tier": "Platinum"}]}