{"data": [{"team_id": 946, "image_id": 1, "team_number": "17-5079", "image": "Windows10_cp17_state_pgsms", "duration": "170:11:50", "found": 7, "remaining": 24, "penalties": 0, "code": "T", "ccs_score": 27, "location": "MD", "division": "NJROTC", "tier": "Platinum"}, {"team_id": 946, "image_id": 4, "team_number": "17-5079", "image": "Server2019_cp17_state_pg", "duration": "171:09:39", "found": 1, "remaining": 30, "penalties": 0, "code": "T", "ccs_score": 4, "location": "MD", "division": "NJROTC", "tier": "Platinum"}]}