{"data": [{"team_id": 757, "image_id": 3, "team_number": "18-0856", "image": "Windows11_cp18_intro_r2_hsms", "duration": "02:28:38", "found": 20, "remaining": 0, "penalties": 0, "code": "", "ccs_score": 100, "location": "HI", "division": "Open"}, {"team_id": 757, "image_id": 1, "team_number": "18-0856", "image": "Mint21_cp18_r2_hs", "duration": "03:06:49", "found": 10, "remaining": 15, "penalties": 0, "code": "", "ccs_score": 39, "location": "HI", "division": "Open"}, {"team_id": 757, "image_id": 4, "team_number": "18-0856", "image": "Server2022_cp18_r2_hs", "duration": "01:47:32", "found": 3, "remaining": 23, "penalties": 0, "code": "S", "ccs_score": 11, "location": "HI", "division": "Open"}]}