{"data": [{"team_id": 155, "image_id": 3, "team_number": "18-0179", "image": "Windows11_cp18_intro_r2_hsms", "duration": "03:12:17", "found": 14, "remaining": 6, "penalties": 0, "code": "", "ccs_score": 72, "location": "MT", "division": "Open"}, {"team_id": 155, "image_id": 1, "team_number": "18-0179", "image": "Mint21_cp18_r2_hs", "duration": "03:21:08", "found": 17, "remaining": 8, "penalties": 0, "code": "", "ccs_score": 66, "location": "MT", "division": "Open"}, {"team_id": 155, "image_id": 4, "team_number": "18-0179", "image": "Server2022_cp18_r2_hs", "duration": "03:21:50", "found": 16, "remaining": 10, "penalties": 0, "code": "", "ccs_score": 63, "location": "MT", "division": "Open"}]}