{"data": [{"team_id": 593, "image_id": 3, "team_number": "18-0664", "image": "Windows11_cp18_intro_r2_hsms", "duration": "03:47:33", "found": 18, "remaining": 2, "penalties": 0, "code": "", "ccs_score": 90, "location": "TX", "division": "Open"}, {"team_id": 593, "image_id": 1, "team_number": "18-0664", "image": "Mint21_cp18_r2_hs", "duration": "03:50:50", "found": 20, "remaining": 5, "penalties": 0, "code": "", "ccs_score": 81, "location": "TX", "division": "Open"}, {"team_id": 593, "image_id": 4, "team_number": "18-0664", "image": "Server2022_cp18_r2_hs", "duration": "03:42:34", "found": 19, "remaining": 7, "penalties": 0, "code": "", "ccs_score": 75, "location": "TX", "division": "Open"}]}