{"data": [{"team_id": 865, "image_id": 3, "team_number": "18-0964", "image": "Windows11_cp18_intro_r2_hsms", "duration": "03:38:37", "found": 12, "remaining": 8, "penalties": 0, "code": "", "ccs_score": 57, "location": "CA", "division": "NJROTC"}, {"team_id": 865, "image_id": 1, "team_number": "18-0964", "image": "Mint21_cp18_r2_hs", "duration": "03:39:35", "found": 14, "remaining": 11, "penalties": 0, "code": "", "ccs_score": 56, "location": "CA", "division": "NJROTC"}, {"team_id": 865, "image_id": 4, "team_number": "18-0964", "image": "Server2022_cp18_r2_hs", "duration": "03:39:50", "found": 13, "remaining": 13, "penalties": 0, "code": "", "ccs_score": 48, "location": "CA", "division": "NJROTC"}]}