{"data": [{"team_id": 226, "image_id": 3, "team_number": "18-0261", "image": "Windows11_cp18_intro_r2_hsms", "duration": "03:24:50", "found": 12, "remaining": 8, "penalties": 0, "code": "", "ccs_score": 58, "location": "RI", "division": "Open"}, {"team_id": 226, "image_id": 1, "team_number": "18-0261", "image": "Mint21_cp18_r2_hs", "duration": "03:00:52", "found": 14, "remaining": 11, "penalties": 0, "code": "", "ccs_score": 57, "location": "RI", "division": "Open"}, {"team_id": 226, "image_id": 4, "team_number": "18-0261", "image": "Server2022_cp18_r2_hs", "duration": "03:36:50", "found": 12, "remaining": 14, "penalties": 0, "code": "", "ccs_score": 50, "location": "RI", "division": "Open"}]}