{"data": [{"team_id": 3843, "image_id": 3, "team_number": "18-4197", "image": "Windows11_cp18_intro_r2_hsms", "duration": "01:55:50", "found": 5, "remaining": 15, "penalties": 0, "code": "", "ccs_score": 26, "location": "WA", "division": "Open"}, {"team_id": 3843, "image_id": 4, "team_number": "18-4197", "image": "Server2022_cp18_r2_hs", "duration": "01:53:25", "found": 4, "remaining": 22, "penalties": 0, "code": "", "ccs_score": 12, "location": "WA", "division": "Open"}, {"team_id": 3843, "image_id": 1, "team_number": "18-4197", "image": "Mint21_cp18_r2_hs", "duration": "01:54:00", "found": 3, "remaining": 22, "penalties": 0, "code": "", "ccs_score": 9, "location": "WA", "division": "Open"}]}