{"data": [{"team_id": 1096, "image_id": 5, "team_number": "18-0561", "image": "Ubuntu24_cp18_state_pg", "duration": "03:59:48", "found": 10, "remaining": 16, "penalties": 0, "code": "", "ccs_score": 42, "location": "IL", "division": "CAP", "tier": "Gold"}, {"team_id": 1096, "image_id": 4, "team_number": "18-0561", "image": "Server2022_cp18_state_pgsms", "duration": "03:46:00", "found": 11, "remaining": 20, "penalties": 0, "code": "", "ccs_score": 26, "location": "IL", "division": "CAP", "tier": "Gold"}, {"team_id": 1096, "image_id": 3, "team_number": "18-0561", "image": "Mint21_cp18_state_gsms", "duration": "03:45:49", "found": 8, "remaining": 24, "penalties": 0, "code": "", "ccs_score": 19, "location": "IL", "division": "CAP", "tier": "Gold"}]}