{"data": [{"team_id": 374, "image_id": 5, "team_number": "18-1379", "image": "Ubuntu24_cp18_state_pg", "duration": "03:54:37", "found": 11, "remaining": 15, "penalties": 0, "code": "", "ccs_score": 47, "location": "VA", "division": "CAP", "tier": "Platinum"}, {"team_id": 374, "image_id": 4, "team_number": "18-1379", "image": "Server2022_cp18_state_pgsms", "duration": "03:48:50", "found": 15, "remaining": 16, "penalties": 0, "code": "", "ccs_score": 44, "location": "VA", "division": "CAP", "tier": "Platinum"}, {"team_id": 374, "image_id": 2, "team_number": "18-1379", "image": "Mint21_cp18_state_p", "duration": "03:56:39", "found": 12, "remaining": 26, "penalties": 0, "code": "", "ccs_score": 25, "location": "VA", "division": "CAP", "tier": "Platinum"}]}