{"data": [{"team_id": 3107, "image_id": 1, "team_number": "18-1478", "image": "Ubuntu24_cp18_state_sms", "duration": "03:43:50", "found": 9, "remaining": 9, "penalties": 0, "code": "", "ccs_score": 55, "location": "MO", "division": "Middle School", "tier": "Middle School"}, {"team_id": 3107, "image_id": 3, "team_number": "18-1478", "image": "Mint21_cp18_state_gsms", "duration": "03:41:44", "found": 10, "remaining": 22, "penalties": 0, "code": "", "ccs_score": 30, "location": "MO", "division": "Middle School", "tier": "Middle School"}, {"team_id": 3107, "image_id": 4, "team_number": "18-1478", "image": "Server2022_cp18_state_pgsms", "duration": "03:28:00", "found": 10, "remaining": 21, "penalties": 0, "code": "", "ccs_score": 26, "location": "MO", "division": "Middle School", "tier": "Middle School"}]}