{"data": [{"team_id": 309, "image_id": 5, "team_number": "18-1106", "image": "Ubuntu24_cp18_state_pg", "duration": "03:40:43", "found": 18, "remaining": 8, "penalties": 0, "code": "", "ccs_score": 70, "location": "TX", "division": "Open", "tier": "Platinum"}, {"team_id": 309, "image_id": 2, "team_number": "18-1106", "image": "Mint21_cp18_state_p", "duration": "03:55:29", "found": 16, "remaining": 22, "penalties": 0, "code": "", "ccs_score": 36, "location": "TX", "division": "Open", "tier": "Platinum"}, {"team_id": 309, "image_id": 4, "team_number": "18-1106", "image": "Server2022_cp18_state_pgsms", "duration": "03:56:47", "found": 12, "remaining": 19, "penalties": 0, "code": "", "ccs_score": 34, "location": "TX", "division": "Open", "tier": "Platinum"}]}