{"data": [{"team_id": 1416, "image_id": 5, "team_number": "18-1804", "image": "Ubuntu24_cp18_state_pg", "duration": "02:17:19", "found": 11, "remaining": 15, "penalties": 0, "code": "", "ccs_score": 47, "location": "VA", "division": "Open", "tier": "Gold"}, {"team_id": 1416, "image_id": 4, "team_number": "18-1804", "image": "Server2022_cp18_state_pgsms", "duration": "03:27:40", "found": 11, "remaining": 20, "penalties": 0, "code": "", "ccs_score": 33, "location": "VA", "division": "Open", "tier": "Gold"}, {"team_id": 1416, "image_id": 3, "team_number": "18-1804", "image": "Mint21_cp18_state_gsms", "duration": "02:18:51", "found": 8, "remaining": 24, "penalties": 0, "code": "", "ccs_score": 28, "location": "VA", "division": "Open", "tier": "Gold"}]}