{"data": [{"team_id": 796, "image_id": 5, "team_number": "18-3288", "image": "Ubuntu24_cp18_state_pg", "duration": "03:50:50", "found": 16, "remaining": 10, "penalties": 0, "code": "", "ccs_score": 62, "location": "CA", "division": "NJROTC", "tier": "Platinum"}, {"team_id": 796, "image_id": 4, "team_number": "18-3288", "image": "Server2022_cp18_state_pgsms", "duration": "03:55:59", "found": 19, "remaining": 12, "penalties": 0, "code": "", "ccs_score": 55, "location": "CA", "division": "NJROTC", "tier": "Platinum"}, {"team_id": 796, "image_id": 2, "team_number": "18-3288", "image": "Mint21_cp18_state_p", "duration": "03:46:47", "found": 14, "remaining": 24, "penalties": 0, "code": "", "ccs_score": 39, "location": "CA", "division": "NJROTC", "tier": "Platinum"}]}