{"data": [{"team_id": 3307, "image_id": 1, "team_number": "18-3455", "image": "Ubuntu24_cp18_state_sms", "duration": "03:04:04", "found": 4, "remaining": 14, "penalties": 0, "code": "", "ccs_score": 30, "location": "MA", "division": "Middle School", "tier": "Middle School"}, {"team_id": 3307, "image_id": 3, "team_number": "18-3455", "image": "Mint21_cp18_state_gsms", "duration": "03:47:40", "found": 6, "remaining": 26, "penalties": 0, "code": "", "ccs_score": 19, "location": "MA", "division": "Middle School", "tier": "Middle School"}, {"team_id": 3307, "image_id": 4, "team_number": "18-3455", "image": "Server2022_cp18_state_pgsms", "duration": "03:47:50", "found": 6, "remaining": 25, "penalties": 0, "code": "", "ccs_score": 12, "location": "MA", "division": "Middle School", "tier": "Middle School"}]}