{"data": [{"team_id": 2876, "image_id": 1, "team_number": "18-4358", "image": "Ubuntu24_cp18_state_sms", "duration": "03:33:42", "found": 11, "remaining": 7, "penalties": 0, "code": "", "ccs_score": 65, "location": "FL", "division": "Open", "tier": "Silver"}, {"team_id": 2876, "image_id": 3, "team_number": "18-4358", "image": "Mint21_cp18_state_gsms", "duration": "02:54:11", "found": 15, "remaining": 17, "penalties": 0, "code": "", "ccs_score": 46, "location": "FL", "division": "Open", "tier": "Silver"}, {"team_id": 2876, "image_id": 4, "team_number": "18-4358", "image": "Server2022_cp18_state_pgsms", "duration": "03:36:48", "found": 6, "remaining": 25, "penalties": 0, "code": "", "ccs_score": 17, "location": "FL", "division": "Open", "tier": "Silver"}]}