{"data": [{"team_id": 1876, "image_id": 1, "team_number": "17-1980", "image": "Ubuntu22_cp17_r1", "duration": "00:34:50", "found": 17, "remaining": 0, "penalties": 0, "code": "", "ccs_score": 100, "location": "CA", "division": "Open", "tier": "High School"}, {"team_id": 1876, "image_id": 2, "team_number": "17-1980", "image": "Windows10_cp17_r1", "duration": "02:18:15", "found": 19, "remaining": 0, "penalties": 0, "code": "", "ccs_score": 100, "location": "CA", "division": "Open", "tier": "High School"}]}