{"data": [{"team_id": 2632, "image_id": 2, "team_number": "17-2771", "image": "Windows10_cp17_r1", "duration": "03:36:33", "found": 18, "remaining": 1, "penalties": 0, "code": "", "ccs_score": 95, "location": "AL", "division": "AFJROTC", "tier": "High School"}, {"team_id": 2632, "image_id": 1, "team_number": "17-2771", "image": "Ubuntu22_cp17_r1", "duration": "02:58:49", "found": 16, "remaining": 1, "penalties": 0, "code": "", "ccs_score": 94, "location": "AL", "division": "AFJROTC", "tier": "High School"}]}