{"data": [{"team_id": 2503, "image_id": 1, "team_number": "17-2639", "image": "Ubuntu22_cp17_r1", "duration": "02:46:49", "found": 17, "remaining": 0, "penalties": 0, "code": "", "ccs_score": 100, "location": "VA", "division": "Open", "tier": "High School"}, {"team_id": 2503, "image_id": 2, "team_number": "17-2639", "image": "Windows10_cp17_r1", "duration": "03:55:50", "found": 16, "remaining": 3, "penalties": 0, "code": "", "ccs_score": 85, "location": "VA", "division": "Open", "tier": "High School"}]}