{"data": [{"team_id": 3245, "image_id": 2, "team_number": "17-3404", "image": "Windows10_cp17_r1", "duration": "01:44:04", "found": 14, "remaining": 5, "penalties": 0, "code": "", "ccs_score": 75, "location": "WA", "division": "AJROTC", "tier": "High School"}, {"team_id": 3245, "image_id": 1, "team_number": "17-3404", "image": "Ubuntu22_cp17_r1", "duration": "00:36:06", "found": 1, "remaining": 16, "penalties": 0, "code": "", "ccs_score": 10, "location": "WA", "division": "AJROTC", "tier": "High School"}]}