{"data": [{"team_id": 3176, "image_id": 1, "team_number": "17-3334", "image": "Ubuntu22_cp17_r1", "duration": "02:50:52", "found": 17, "remaining": 0, "penalties": 0, "code": "", "ccs_score": 100, "location": "VA", "division": "MCJROTC", "tier": "High School"}, {"team_id": 3176, "image_id": 2, "team_number": "17-3334", "image": "Windows10_cp17_r1", "duration": "03:51:50", "found": 14, "remaining": 5, "penalties": 1, "code": "", "ccs_score": 71, "location": "VA", "division": "MCJROTC", "tier": "High School"}]}