{"data": [{"team_id": 3606, "image_id": 2, "team_number": "17-3779", "image": "Windows10_cp17_r1", "duration": "03:54:19", "found": 8, "remaining": 11, "penalties": 0, "code": "", "ccs_score": 48, "location": "DE", "division": "MCJROTC", "tier": "High School"}, {"team_id": 3606, "image_id": 1, "team_number": "17-3779", "image": "Ubuntu22_cp17_r1", "duration": "03:09:50", "found": 7, "remaining": 10, "penalties": 0, "code": "", "ccs_score": 46, "location": "DE", "division": "MCJROTC", "tier": "High School"}]}