{"data": [{"team_id": 3043, "image_id": 2, "team_number": "17-3197", "image": "Windows10_cp17_r1", "duration": "03:52:50", "found": 17, "remaining": 2, "penalties": 0, "code": "", "ccs_score": 90, "location": "AL", "division": "AJROTC", "tier": "High School"}, {"team_id": 3043, "image_id": 1, "team_number": "17-3197", "image": "Ubuntu22_cp17_r1", "duration": "03:52:49", "found": 13, "remaining": 4, "penalties": 0, "code": "", "ccs_score": 77, "location": "AL", "division": "AJROTC", "tier": "High School"}]}