{"data": [{"team_id": 4188, "image_id": 1, "team_number": "17-4380", "image": "Ubuntu22_cp17_r1", "duration": "02:23:51", "found": 14, "remaining": 3, "penalties": 0, "code": "", "ccs_score": 85, "location": "WA", "division": "Open", "tier": "High School"}, {"team_id": 4188, "image_id": 2, "team_number": "17-4380", "image": "Windows10_cp17_r1", "duration": "02:54:36", "found": 15, "remaining": 4, "penalties": 0, "code": "", "ccs_score": 80, "location": "WA", "division": "Open", "tier": "High School"}]}