{"data": [{"team_id": 587, "image_id": 1, "team_number": "18-2195", "image": "Server2019_cp18_sf_pg", "duration": "03:27:17", "found": 5, "remaining": 30, "penalties": 0, "code": "", "ccs_score": 8, "location": "NC", "division": "CAP", "tier": "Gold"}, {"team_id": 587, "image_id": 4, "team_number": "18-2195", "image": "Mint21_cp18_sf_pgsms", "duration": "03:27:48", "found": 5, "remaining": 35, "penalties": 0, "code": "", "ccs_score": 6, "location": "NC", "division": "CAP", "tier": "Gold"}, {"team_id": 587, "image_id": 3, "team_number": "18-2195", "image": "Server2022_cp18_sf_gsms", "duration": "01:09:33", "found": 0, "remaining": 32, "penalties": 0, "code": "", "ccs_score": 0, "location": "NC", "division": "CAP", "tier": "Gold"}]}